PSD/Lab6/automat2.v
module fsm(
    input [1:0] in,
    input clk, reset,
    output reg [2:0] out
);

    reg [1:0] cs, ns;

    always @(posedge clk or posedge reset) begin
        if (reset)
            cs <= 2'b00;
        else
            cs <= ns;
    end

    always @(posedge clk) begin
        ns = cs;
        out = 3'b000;
        

        case(cs)
            2'b00: begin
                if (in[1] == 1'b0) begin // 0X
                    ns = 2'b00;
                    out = 3'b000;
                end else if (in == 2'b10) begin
                    ns = 2'b01;
                    out = 3'b001;
                end
            end

            2'b01: begin
                if (in == 2'b11 || in == 2'b00) begin
                    ns = 2'b00;
                    out = 3'b000;
                end else if (in == 2'b01) begin
                    ns = 2'b10;
                    out = 3'b010;
                end else if (in == 2'b10) begin
                    ns = 2'b01;
                    out = 3'b001;
                end
            end
            
            2'b10: begin
               if (in == 2'b00) begin
                    ns = 2'b01;
                    out = 3'b001;
                end else if (in == 2'b11 || in == 2'b01) begin
                    ns = 2'b10;
                    out = 3'b010;
                end else if (in == 2'b10) begin
                    ns = 2'b11;
                    out = 3'b100;
                end
            end

            2'b11: begin
              if (in == 2'b11 || in == 2'b01) begin
                    ns = 2'b00;
                    out = 3'b111;
                end else if (in == 2'b00) begin
                    ns = 2'b10;
                    out = 3'b010;
                end else if (in == 2'b10) begin
                    ns = 2'b11;
                    out = 3'b100;
                end
            end
        endcase
    end

endmodule

PSD/Lab6/test2.v
`timescale 1ns / 1ps

module fsm_tb();
    reg [1:0] in;
    reg clk;
    reg reset;
    wire [2:0] out;

    fsm uut (
        .in(in),
        .clk(clk),
        .reset(reset),
        .out(out)
    );

    always #5 clk = ~clk;

    initial begin
        $dumpfile("fsm_test.vcd");
        $dumpvars(0, fsm_tb);

        clk = 0;
        reset = 1;
        in = 2'b00;

        #15 reset = 0;
        #10 in = 2'b10; 
        #10 in = 2'b01; 
        #10 in = 2'b10; 
        #10 in = 2'b11;
        #10 in = 2'b00;
        
        #20 $finish;
    end
endmodule

PSD/Lab6/fsm_test.vcd
$date
	Thu Mar 26 17:36:31 2026
$end
$version
	Icarus Verilog
$end
$timescale
	1ps
$end
$scope module fsm_tb $end
$var wire 3 ! out [2:0] $end
$var reg 1 " clk $end
$var reg 2 # in [1:0] $end
$var reg 1 $ reset $end
$scope module uut $end
$var wire 1 " clk $end
$var wire 2 % in [1:0] $end
$var wire 1 $ reset $end
$var reg 2 & cs [1:0] $end
$var reg 2 ' ns [1:0] $end
$var reg 3 ( out [2:0] $end
$upscope $end
$upscope $end
$enddefinitions $end
$comment Show the parameter values. $end
$dumpall
$end
#0
$dumpvars
bx (
bx '
b0 &
b0 %
1$
b0 #
0"
bx !
$end
#5000
b0 !
b0 (
b0 '
1"
#10000
0"
#15000
1"
0$
#20000
0"
#25000
b1 !
b1 (
b1 '
1"
b10 #
b10 %
#30000
0"
#35000
b1 &
b0 !
b0 (
b0 '
1"
b1 #
b1 %
#40000
0"
#45000
b0 &
b1 !
b1 (
b1 '
1"
b10 #
b10 %
#50000
0"
#55000
b1 &
b0 !
b0 (
b0 '
1"
b11 #
b11 %
#60000
0"
#65000
b0 &
b0 '
1"
b0 #
b0 %
